LICENSE.txt
MANIFEST.in
README.txt
dbgpClient.py
setup.py
bin/pydbgp
bin/pydbgpproxy
dbgp/__init__.py
dbgp/_pyclient.py
dbgp/client.py
dbgp/common.py
dbgp/listcmd.py
dbgp/server.py
dbgp/serverBase.py
komodo_python3_dbgp.egg-info/PKG-INFO
komodo_python3_dbgp.egg-info/SOURCES.txt
komodo_python3_dbgp.egg-info/dependency_links.txt
komodo_python3_dbgp.egg-info/not-zip-safe
komodo_python3_dbgp.egg-info/top_level.txt
libs/linux-x86/_client31.so
libs/linux-x86/_client32.cpython-32m.so
libs/linux-x86/_client33.cpython-33m.so
libs/linux-x86_64/_client31.so
libs/linux-x86_64/_client32.cpython-32m.so
libs/linux-x86_64/_client33.cpython-33m.so
libs/win32-x86/_client31.pyd
libs/win32-x86/_client32.pyd
libs/win32-x86/_client33.pyd