Metadata-Version: 1.1
Name: komodo-python3-dbgp
Version: 11.0
Summary: The ActiveState Komodo DBGP server
Home-page: http://github.com/agroszer/komodo-python3-dbgp
Author: Adam Groszer
Author-email: agroszer@gmail.com
License: UNKNOWN
Platform: UNKNOWN
Classifier: Development Status :: 5 - Production/Stable
Classifier: Intended Audience :: Developers
Classifier: Programming Language :: Python
Classifier: Programming Language :: Python :: 3
Classifier: Programming Language :: Python :: 3.1
Classifier: Programming Language :: Python :: 3.2
Classifier: Programming Language :: Python :: 3.3
Classifier: Programming Language :: Python :: Implementation :: CPython
